{
  "version_id": 3,
  "timestamp": "day 1, 06:00:00",
  "changes": {
    "mutable": {
      "locations": [
        {
          "id": 29,
          "description": "A large, empty 10x10 meter clearing starting from the anchor point, extending away from the occupied zone.",
          "groups": [
            {
              "description": "A Forest clearing occupies the entire space, serving as the base for the other objects. A Granite boulder is positioned in the center-left area, with a River pebble resting on top of it. A patch of Wild lavender is located in the northern section, while an Oak stump is situated in the southeastern part of the clearing.",
              "cell_indices": [
                "-5:-12:0",
                "-4:-12:0",
                "-3:-12:0",
                "-2:-12:0",
                "-1:-12:0",
                "0:-12:0",
                "1:-12:0",
                "2:-12:0",
                "3:-12:0",
                "4:-12:0",
                "-5:-13:0",
                "-4:-13:0",
                "-3:-13:0",
                "-2:-13:0",
                "-1:-13:0",
                "0:-13:0",
                "1:-13:0",
                "2:-13:0",
                "3:-13:0",
                "4:-13:0",
                "-5:-14:0",
                "-4:-14:0",
                "-3:-14:0",
                "-2:-14:0",
                "-1:-14:0",
                "0:-14:0",
                "1:-14:0",
                "2:-14:0",
                "3:-14:0",
                "4:-14:0",
                "-5:-15:0",
                "-4:-15:0",
                "-3:-15:0",
                "-2:-15:0",
                "-1:-15:0",
                "0:-15:0",
                "1:-15:0",
                "2:-15:0",
                "3:-15:0",
                "4:-15:0",
                "-5:-16:0",
                "-4:-16:0",
                "-3:-16:0",
                "-2:-16:0",
                "-1:-16:0",
                "0:-16:0",
                "1:-16:0",
                "2:-16:0",
                "3:-16:0",
                "4:-16:0",
                "-5:-17:0",
                "-4:-17:0",
                "-3:-17:0",
                "-2:-17:0",
                "-1:-17:0",
                "0:-17:0",
                "1:-17:0",
                "2:-17:0",
                "3:-17:0",
                "4:-17:0",
                "-5:-18:0",
                "-4:-18:0",
                "-3:-18:0",
                "-2:-18:0",
                "-1:-18:0",
                "0:-18:0",
                "1:-18:0",
                "2:-18:0",
                "3:-18:0",
                "4:-18:0",
                "-5:-19:0",
                "-4:-19:0",
                "-3:-19:0",
                "-2:-19:0",
                "-1:-19:0",
                "0:-19:0",
                "1:-19:0",
                "2:-19:0",
                "3:-19:0",
                "4:-19:0",
                "-5:-20:0",
                "-4:-20:0",
                "-3:-20:0",
                "-2:-20:0",
                "-1:-20:0",
                "0:-20:0",
                "1:-20:0",
                "2:-20:0",
                "3:-20:0",
                "4:-20:0",
                "-5:-21:0",
                "-4:-21:0",
                "-3:-21:0",
                "-2:-21:0",
                "-1:-21:0",
                "0:-21:0",
                "1:-21:0",
                "2:-21:0",
                "3:-21:0",
                "4:-21:0"
              ]
            }
          ],
          "last_update_time": "day 1, 06:00:00"
        }
      ],
      "objects": [
        {
          "id": 24,
          "cell_indices": [
            "-5:-12:0",
            "-4:-12:0",
            "-3:-12:0",
            "-2:-12:0",
            "-1:-12:0",
            "0:-12:0",
            "1:-12:0",
            "2:-12:0",
            "3:-12:0",
            "4:-12:0",
            "-5:-13:0",
            "-4:-13:0",
            "-3:-13:0",
            "-2:-13:0",
            "-1:-13:0",
            "0:-13:0",
            "1:-13:0",
            "2:-13:0",
            "3:-13:0",
            "4:-13:0",
            "-5:-14:0",
            "-4:-14:0",
            "-3:-14:0",
            "-2:-14:0",
            "-1:-14:0",
            "0:-14:0",
            "1:-14:0",
            "2:-14:0",
            "3:-14:0",
            "4:-14:0",
            "-5:-15:0",
            "-4:-15:0",
            "-3:-15:0",
            "-2:-15:0",
            "-1:-15:0",
            "0:-15:0",
            "1:-15:0",
            "2:-15:0",
            "3:-15:0",
            "4:-15:0",
            "-5:-16:0",
            "-4:-16:0",
            "-3:-16:0",
            "-2:-16:0",
            "-1:-16:0",
            "0:-16:0",
            "1:-16:0",
            "2:-16:0",
            "3:-16:0",
            "4:-16:0",
            "-5:-17:0",
            "-4:-17:0",
            "-3:-17:0",
            "-2:-17:0",
            "-1:-17:0",
            "0:-17:0",
            "1:-17:0",
            "2:-17:0",
            "3:-17:0",
            "4:-17:0",
            "-5:-18:0",
            "-4:-18:0",
            "-3:-18:0",
            "-2:-18:0",
            "-1:-18:0",
            "0:-18:0",
            "1:-18:0",
            "2:-18:0",
            "3:-18:0",
            "4:-18:0",
            "-5:-19:0",
            "-4:-19:0",
            "-3:-19:0",
            "-2:-19:0",
            "-1:-19:0",
            "0:-19:0",
            "1:-19:0",
            "2:-19:0",
            "3:-19:0",
            "4:-19:0",
            "-5:-20:0",
            "-4:-20:0",
            "-3:-20:0",
            "-2:-20:0",
            "-1:-20:0",
            "0:-20:0",
            "1:-20:0",
            "2:-20:0",
            "3:-20:0",
            "4:-20:0",
            "-5:-21:0",
            "-4:-21:0",
            "-3:-21:0",
            "-2:-21:0",
            "-1:-21:0",
            "0:-21:0",
            "1:-21:0",
            "2:-21:0",
            "3:-21:0",
            "4:-21:0"
          ],
          "history": [
            "A large, open 10x10 meter forest clearing. The ground is composed of flat, packed earth and patches of wild grass, providing a wide and unobstructed natural space."
          ]
        },
        {
          "id": 0,
          "cell_indices": [
            "-1:1:0",
            "0:1:0",
            "1:1:0",
            "-1:0:0",
            "0:0:0",
            "1:0:0",
            "-1:-1:0",
            "0:-1:0",
            "1:-1:0"
          ],
          "history": [
            "A rustic floor made of wide, hand-hewn wooden planks, showing signs of wear from heavy boots."
          ]
        },
        {
          "id": 1,
          "cell_indices": [
            "-1:1:0",
            "0:1:0",
            "1:1:0",
            "-1:0:0",
            "1:0:0",
            "-1:-1:0",
            "0:-1:0",
            "1:-1:0"
          ],
          "history": [
            "Sturdy log walls notched together and sealed with dried moss to insulate the cabin against the forest chill."
          ]
        },
        {
          "id": 2,
          "cell_indices": [
            "0:-1:0"
          ],
          "history": [
            "A heavy wooden door with iron hinges and a simple latch, serving as the main entrance."
          ]
        },
        {
          "id": 3,
          "cell_indices": [
            "0:1:0"
          ],
          "history": [
            "A small rectangular window opening with a wooden shutter, currently closed."
          ]
        },
        {
          "id": 4,
          "cell_indices": [
            "1:1:0"
          ],
          "history": [
            "A large fireplace built from river stones, currently cold and containing only grey ash."
          ]
        },
        {
          "id": 5,
          "cell_indices": [
            "1:1:0"
          ],
          "history": [
            "A stack of dry, split firewood logs piled neatly on the floor beside the stone fireplace."
          ]
        },
        {
          "id": 6,
          "cell_indices": [
            "-1:0:0"
          ],
          "history": [
            "A powerful recurve hunting bow made of dark wood and bone, leaning against the log wall."
          ]
        },
        {
          "id": 7,
          "cell_indices": [
            "-1:0:0"
          ],
          "history": [
            "A leather quiver containing several arrows with sharp flint heads and bird-feather fletching."
          ]
        },
        {
          "id": 8,
          "cell_indices": [
            "0:0:0"
          ],
          "history": [
            "Name: Maza. Race: Orc. Gender: Female. Height: 178cm. Weight: 82kg. Build: Athletic and lean. Distinctive Features: Pale green skin, yellow eyes, two small tusks protruding from her lower lip, and black hair tied in a high ponytail."
          ]
        },
        {
          "id": 9,
          "parent_object_id": 8,
          "history": [
            "Layer 1: Simple linen undergarments consisting of a supportive chest wrap and a loincloth."
          ]
        },
        {
          "id": 10,
          "parent_object_id": 8,
          "history": [
            "Layer 2: A set of practical hunting clothes made of dark deerskin, including a sleeveless tunic and fitted trousers."
          ]
        },
        {
          "id": 11,
          "parent_object_id": 8,
          "history": [
            "Layer 3: A thick fur-lined leather mantle draped over the shoulders for warmth in the forest."
          ]
        },
        {
          "id": 12,
          "parent_object_id": 8,
          "history": [
            "Layer 4: A necklace made of wolf teeth and leather cord, a trophy from a previous hunt."
          ]
        },
        {
          "id": 13,
          "cell_indices": [
            "0:1:0"
          ],
          "history": [
            "A large, rustic fireplace built from heavy river stones. The hearth is currently cold and contains no lit embers."
          ]
        },
        {
          "id": 14,
          "parent_object_id": 13,
          "history": [
            "A neat stack of dry, split oak firewood placed within the fireplace hearth."
          ]
        },
        {
          "id": 15,
          "cell_indices": [
            "-1:0:0"
          ],
          "history": [
            "A powerful recurve bow crafted from dark yew wood and reinforced with horn, leaning against a support."
          ]
        },
        {
          "id": 16,
          "cell_indices": [
            "-1:0:0"
          ],
          "history": [
            "A rugged leather quiver with a thick shoulder strap, designed for quick access to ammunition."
          ]
        },
        {
          "id": 17,
          "parent_object_id": 16,
          "history": [
            "A bundle of twenty hunting arrows with sharp flint heads and grey goose feather fletching."
          ]
        },
        {
          "id": 19,
          "cell_indices": [
            "0:-2:0",
            "0:-3:0",
            "0:-4:0",
            "0:-5:0",
            "0:-6:0",
            "0:-7:0",
            "0:-8:0",
            "0:-9:0",
            "0:-10:0",
            "0:-11:0"
          ],
          "history": [
            "A long, narrow dirt road made of packed earth and scattered gravel, extending southward from the cabin\u0027s entrance."
          ]
        },
        {
          "id": 20,
          "cell_indices": [
            "0:-2:0"
          ],
          "history": [
            "A weathered wooden signpost standing at the start of the dirt path, featuring a crude carving of a hunting bow pointing back toward the cabin."
          ]
        },
        {
          "id": 21,
          "cell_indices": [
            "0:-7:0"
          ],
          "history": [
            "A small cairn of stacked grey river stones, likely placed here as a navigational marker by a traveler or hunter."
          ]
        },
        {
          "id": 22,
          "cell_indices": [
            "0:-10:0"
          ],
          "history": [
            "A rusted iron animal trap, its jaws open and partially buried under a layer of loose dirt and forest debris."
          ]
        },
        {
          "id": 24,
          "cell_indices": [
            "-5:-12:0",
            "-4:-12:0",
            "-3:-12:0",
            "-2:-12:0",
            "-1:-12:0",
            "0:-12:0",
            "1:-12:0",
            "2:-12:0",
            "3:-12:0",
            "4:-12:0",
            "-5:-13:0",
            "-4:-13:0",
            "-3:-13:0",
            "-2:-13:0",
            "-1:-13:0",
            "0:-13:0",
            "1:-13:0",
            "2:-13:0",
            "3:-13:0",
            "4:-13:0",
            "-5:-14:0",
            "-4:-14:0",
            "-3:-14:0",
            "-2:-14:0",
            "-1:-14:0",
            "0:-14:0",
            "1:-14:0",
            "2:-14:0",
            "3:-14:0",
            "4:-14:0",
            "-5:-15:0",
            "-4:-15:0",
            "-3:-15:0",
            "-2:-15:0",
            "-1:-15:0",
            "0:-15:0",
            "1:-15:0",
            "2:-15:0",
            "3:-15:0",
            "4:-15:0",
            "-5:-16:0",
            "-4:-16:0",
            "-3:-16:0",
            "-2:-16:0",
            "-1:-16:0",
            "0:-16:0",
            "1:-16:0",
            "2:-16:0",
            "3:-16:0",
            "4:-16:0",
            "-5:-17:0",
            "-4:-17:0",
            "-3:-17:0",
            "-2:-17:0",
            "-1:-17:0",
            "0:-17:0",
            "1:-17:0",
            "2:-17:0",
            "3:-17:0",
            "4:-17:0",
            "-5:-18:0",
            "-4:-18:0",
            "-3:-18:0",
            "-2:-18:0",
            "-1:-18:0",
            "0:-18:0",
            "1:-18:0",
            "2:-18:0",
            "3:-18:0",
            "4:-18:0",
            "-5:-19:0",
            "-4:-19:0",
            "-3:-19:0",
            "-2:-19:0",
            "-1:-19:0",
            "0:-19:0",
            "1:-19:0",
            "2:-19:0",
            "3:-19:0",
            "4:-19:0",
            "-5:-20:0",
            "-4:-20:0",
            "-3:-20:0",
            "-2:-20:0",
            "-1:-20:0",
            "0:-20:0",
            "1:-20:0",
            "2:-20:0",
            "3:-20:0",
            "4:-20:0",
            "-5:-21:0",
            "-4:-21:0",
            "-3:-21:0",
            "-2:-21:0",
            "-1:-21:0",
            "0:-21:0",
            "1:-21:0",
            "2:-21:0",
            "3:-21:0",
            "4:-21:0"
          ],
          "history": [
            "A large, open 10x10 meter forest clearing. The ground is composed of flat, packed earth and patches of wild grass, providing a wide and unobstructed natural space."
          ]
        },
        {
          "id": 25,
          "cell_indices": [
            "-2:-15:0"
          ],
          "history": [
            "A massive, moss-covered granite boulder resting firmly in the earth, its surface weathered by years of exposure to the elements."
          ]
        },
        {
          "id": 26,
          "cell_indices": [
            "3:-19:0"
          ],
          "history": [
            "A weathered oak stump, bleached grey by the sun, featuring deep cracks and jagged edges where the tree once stood."
          ]
        },
        {
          "id": 27,
          "cell_indices": [
            "0:-13:0"
          ],
          "history": [
            "A small, isolated patch of hardy wild lavender growing amidst the tall grass, swaying gently in the wind."
          ]
        },
        {
          "id": 28,
          "parent_object_id": 25,
          "history": [
            "A small, smooth river pebble placed intentionally on the flat top of the mossy boulder."
          ]
        }
      ]
    },
    "immutable": {
      "text": {
        "Text": "Generation Tool: Created location 29: крупная пустая поляна 10x10 без существ",
        "Locations": [],
        "SimulationLog": []
      }
    },
    "temporary": {}
  }
}